Metadata-Version: 2.4
Name: package-creation-tutorial-molka
Version: 0.1.0
Summary: 
Author: molka
Author-email: molka.essid@dauphine.tn
Requires-Python: >=3.11
Classifier: Programming Language :: Python :: 3
Classifier: Programming Language :: Python :: 3.11
Classifier: Programming Language :: Python :: 3.12
Classifier: Programming Language :: Python :: 3.13
Classifier: Programming Language :: Python :: 3.14
Requires-Dist: pre-commit (>=4.5.1,<5.0.0)
Requires-Dist: pytest (>=9.0.2,<10.0.0)
Requires-Dist: pytest-cov (>=7.0.0,<8.0.0)
Requires-Dist: ruff (>=0.14.13,<0.15.0)
Requires-Dist: sphinx (>=6.2,<7.0)
Requires-Dist: sphinx-rtd-theme (>=1.3,<2.0)
